{"synckey":1602914158,"updated":[{"bookId":"23784334","bookmarkId":"23784334_4_1332-1343","createTime":1602914158,"range":"1332-1343","markText":"君子疾没世而名不称焉！","type":1,"chapterUid":4},{"bookId":"23784334","bookmarkId":"23784334_4_1039-1049","createTime":1602914110,"range":"1039-1049","markText":"鼠在所居，人固择地。","type":1,"chapterUid":4},{"bookId":"23784334","bookmarkId":"23784334_4_962-1015","createTime":1602914092,"range":"962-1015","markText":"见到此情此景，李斯不由百感交集，说出了他在中国历史舞台上的第一句台词：“人之贤不肖譬如鼠矣，在所自处耳！”","type":1,"chapterUid":4}],"removed":[],"chapters":[{"title":"一个普通青年的觉醒","chapterUid":4,"chapterIdx":4}],"book":{"bookId":"23784334","version":0,"format":"txt","soldout":0,"bookStatus":1,"cover":"https://cdn.weread.qq.com/weread/cover/86/YueWen_23784334/s_YueWen_23784334.jpg","title":"流血的仕途：李斯与秦帝国（全2册纪念版）","author":"曹昇","coverBoxInfo":{"blurhash":"KsNAVPR*S5~qayRjX9f6of","colors":[{"key":"1/4","hex":"#201b1a"},{"key":"1/6","hex":"#201b1a"},{"key":"1/8","hex":"#201b1a"},{"key":"2/4","hex":"#35302e"},{"key":"2/6","hex":"#35302e"},{"key":"2/8","hex":"#35302e"},{"key":"3/4","hex":"#4c4744"},{"key":"3/6","hex":"#4c4744"},{"key":"3/8","hex":"#4c4744"},{"key":"3/12","hex":"#4c4744"},{"key":"4/6","hex":"#645f5d"},{"key":"4/10","hex":"#645f5d"},{"key":"4/4","hex":"#645f5d"},{"key":"5/10","hex":"#7e7976"},{"key":"5/4","hex":"#7e7976"},{"key":"5/8","hex":"#7e7976"},{"key":"6/4","hex":"#979290"},{"key":"6/6","hex":"#979290"},{"key":"6/8","hex":"#979290"},{"key":"6/12","hex":"#979290"},{"key":"7/8","hex":"#b1acaa"},{"key":"7/10","hex":"#b1acaa"},{"key":"7/12","hex":"#b1acaa"},{"key":"8/4","hex":"#ccc7c4"},{"key":"8/6","hex":"#ccc7c4"},{"key":"8/12","hex":"#ccc7c4"},{"key":"9/2","hex":"#e7e2df"},{"key":"9/12","hex":"#e7e2df"},{"key":"1/100","hex":"#979290"},{"key":"2/100","hex":"#b1acaa"},{"key":"3/100","hex":"#ffffff"},{"key":"4/100","hex":"#F3E8E5"},{"key":"5/100","hex":"#F3E8E5"},{"key":"6/100","hex":"#270500"}],"dominate_color":{"hex":"#efeae7","hsv":[26.07628492834894,3.502534059261861,93.69258850390144]},"custom_cover":"https://weread-1258476243.file.myqcloud.com/bookalphacover/334/23784334/s_23784334.jpg","custom_rec_cover":"https://weread-1258476243.file.myqcloud.com/bookreccover/334/23784334/s_23784334.jpg","colorsPure":["#979290","#b1acaa"]}}}