{"synckey":1605438277,"updated":[{"bookId":"25369595","bookmarkId":"25369595_63_874-1014","chapterUid":63,"markText":"复杂的新情绪也可能是因支撑道德进化而来。这些新情绪包括羞耻（对违反规范的主观惩罚），内疚（对违反预期的主观惩罚），骄傲（对坚守规范的主观报偿），道德义愤（当其他人违反规范时的一种愤怒，就好像他们的行为是针对自己似的），以及轻蔑（对他人的一种持久的贬低，因为他们违反了规范或预期）。","range":"874-1014","createTime":1596632490,"type":1},{"bookId":"25369595","bookmarkId":"25369595_49_524-677","chapterUid":49,"markText":"在开始与人合作之前，我们应该调查一下自己的同伴在过去的表现如何，留意他们每一步的行为；采取一报还一报策略；对合作进行激励和奖赏，对欺骗进行阻止和惩罚；使用情感、道德、宗教和法律系统让我们的同伴表现得规规矩矩；最后，我们每天还要通过一些怪异的、危险的、令人烦恼的行为或是大胆的性行为对他们的承诺强度进行测试。","range":"524-677","createTime":1596586118,"type":1},{"bookId":"25369595","bookmarkId":"25369595_13_506-541","chapterUid":13,"markText":"支配性早已深入人性的最深处，因此，幻想没有支配性的社会关系是不现实的。","range":"506-541","createTime":1596519573,"type":1},{"bookId":"25369595","bookmarkId":"25369595_9_2202-2252","chapterUid":9,"markText":"作为人类微笑行为的进化先驱，这种“龇牙展示”要是被对方明确接收到，就能发挥类似于理毛行为所具有的作用","range":"2202-2252","createTime":1596519250,"type":1},{"bookId":"25369595","bookmarkId":"25369595_9_1982-2014","chapterUid":9,"markText":"相互之间的目光接触也是危险的，因为在猴子的语言中，凝视就是威胁。","range":"2000-2032","createTime":1596519235,"type":1},{"bookId":"25369595","bookmarkId":"25369595_9_888-934","chapterUid":9,"markText":"猕猴不喜欢陌生的同伴，除非对方是潜在的性伙伴，否则陌生猕猴的存在通常都会迅速地引发敌意反应。","range":"906-952","createTime":1596516908,"type":1},{"bookId":"25369595","bookmarkId":"25369595_8_1571-1652","createTime":1596410591,"range":"1571-1652","markText":"当一群乌干达黑猩猩碰上另外一个群体中的某只雄性黑猩猩时，它们将割开对方的喉咙，撕裂对方的睾丸——为了防止对方可能活下来，也为了防止对方有任何未来繁衍的雄心壮志。\n","type":1,"chapterUid":8},{"bookId":"25369595","bookmarkId":"25369595_3_1900-2007","chapterUid":3,"markText":"只有有代价的承诺行为才具有诚实的性质。不痛不痒的话，很廉价，但也很容易作假。只有像雄孔雀那样拖着一条沉重的大尾巴，像瞪羚那样以找死的方式跳跃，像雄狒狒怀抱婴儿那样跟其他狒狒厮打，才能向外界传达自己承诺的可靠和诚实。","range":"1900-2007","createTime":1596408381,"type":1}],"removed":[],"chapters":[{"title":"战，还是不战","chapterUid":9,"chapterIdx":9},{"title":"第二章 痴迷权力与统治","chapterUid":13,"chapterIdx":13},{"title":"寻找正确的搭档","chapterUid":49,"chapterIdx":49},{"title":"最近的过去","chapterUid":63,"chapterIdx":63},{"title":"穴居人的遗产","chapterUid":8,"chapterIdx":8},{"title":"译者的话","chapterUid":3,"chapterIdx":3}],"book":{"bookId":"25369595","version":611990151,"format":"epub","soldout":1,"bookStatus":1,"cover":"https://wfqqreader-1252317822.image.myqcloud.com/cover/595/25369595/s_25369595.jpg","title":"猿猴的把戏：进化论破解人际潜规则","author":"[美]达里奥·马埃斯特里皮埃里","coverBoxInfo":{"blurhash":"KECGMm%1nzWX%g%g~q%NWW","colors":[{"key":"1/4","hex":"#261b00"},{"key":"1/6","hex":"#2a1b00"},{"key":"1/8","hex":"#2e1a00"},{"key":"2/4","hex":"#3a3103"},{"key":"2/6","hex":"#3d3000"},{"key":"2/8","hex":"#3f3000"},{"key":"3/4","hex":"#51481d"},{"key":"3/6","hex":"#544700"},{"key":"3/8","hex":"#564700"},{"key":"3/12","hex":"#594700"},{"key":"4/6","hex":"#6e6013"},{"key":"4/10","hex":"#726000"},{"key":"4/4","hex":"#6b6030"},{"key":"5/10","hex":"#8d7a00"},{"key":"5/4","hex":"#857a47"},{"key":"5/8","hex":"#8b7a00"},{"key":"6/4","hex":"#9e9460"},{"key":"6/6","hex":"#a39443"},{"key":"6/8","hex":"#a69420"},{"key":"6/12","hex":"#aa9400"},{"key":"7/8","hex":"#c1af3e"},{"key":"7/10","hex":"#c4ae08"},{"key":"7/12","hex":"#c6ae00"},{"key":"8/4","hex":"#d3c990"},{"key":"8/6","hex":"#d8c975"},{"key":"8/12","hex":"#e1c900"},{"key":"9/2","hex":"#eae4c3"},{"key":"9/12","hex":"#fde517"},{"key":"1/100","hex":"#a69420"},{"key":"2/100","hex":"#c1af3e"},{"key":"3/100","hex":"#ffffff"},{"key":"4/100","hex":"#F3F1E5"},{"key":"5/100","hex":"#F3F1E5"},{"key":"6/100","hex":"#271E00"}],"dominate_color":{"hex":"#262214","hsv":[44.22951082317332,46.78569095066972,15.029565501470108]},"custom_cover":"https://weread-1258476243.file.myqcloud.com/bookalphacover/595/25369595/s_25369595.jpg","custom_rec_cover":"https://weread-1258476243.file.myqcloud.com/bookreccover/595/25369595/s_25369595.jpg","colorsPure":["#aa9400","#c6ae00"]}}}