{"synckey":1743700266,"updated":[{"bookId":"34538505","bookmarkId":"34538505_5_527-570","chapterUid":108,"markText":"我花了很长的岁月，走过大半个世界，才真正学到什么是爱、什么是命运，以及我们所做的抉择。","range":"427-470","createTime":1673451666,"type":1}],"removed":[],"chapters":[{"title":"第一章","chapterUid":108,"chapterIdx":4}],"book":{"bookId":"34538505","version":1868866028,"format":"epub","soldout":0,"bookStatus":1,"cover":"https://cdn.weread.qq.com/weread/cover/65/yuewen_34538505/s_yuewen_345385051743678934.jpg","title":"项塔兰（2025版）","author":"[澳]格里高利·大卫·罗伯兹","coverBoxInfo":{"blurhash":"KyM6^-jFt600ofM|E+ozjb","colors":[{"key":"1/4","hex":"#331400"},{"key":"1/6","hex":"#3a0f00"},{"key":"1/8","hex":"#410600"},{"key":"2/4","hex":"#462b10"},{"key":"2/6","hex":"#4d2700"},{"key":"2/8","hex":"#522500"},{"key":"3/4","hex":"#604125"},{"key":"3/6","hex":"#673e0f"},{"key":"3/8","hex":"#6c3c00"},{"key":"3/12","hex":"#763600"},{"key":"4/6","hex":"#835626"},{"key":"4/10","hex":"#8e5200"},{"key":"4/4","hex":"#7b5939"},{"key":"5/10","hex":"#ac6b00"},{"key":"5/4","hex":"#957352"},{"key":"5/8","hex":"#a76d24"},{"key":"6/4","hex":"#b08d6b"},{"key":"6/6","hex":"#ba8a56"},{"key":"6/8","hex":"#c3873e"},{"key":"6/12","hex":"#cf8200"},{"key":"7/8","hex":"#dfa158"},{"key":"7/10","hex":"#e79f3e"},{"key":"7/12","hex":"#ee9c18"},{"key":"8/4","hex":"#e5c29c"},{"key":"8/6","hex":"#f1bf87"},{"key":"8/12","hex":"#ffb738"},{"key":"9/2","hex":"#f3e0cb"},{"key":"9/12","hex":"#ffd253"},{"key":"1/100","hex":"#c3873e"},{"key":"2/100","hex":"#dfa158"},{"key":"3/100","hex":"#ffffff"},{"key":"4/100","hex":"#F3EDE5"},{"key":"5/100","hex":"#F3EDE5"},{"key":"6/100","hex":"#271300"}],"dominate_color":{"hex":"#f2cca2","hsv":[31.225549531160064,32.91924075110681,94.89420385731006]},"custom_cover":"https://weread-1258476243.file.myqcloud.com/bookalphacover/505/34538505/s_34538505.jpg","custom_rec_cover":"https://weread-1258476243.file.myqcloud.com/bookreccover/505/34538505/s_34538505.jpg","colorsPure":["#cf8200","#ee9c18"]}}}