{"synckey":1750647719,"updated":[{"bookId":"907585","bookmarkId":"907585_9_4330-4500","chapterUid":9,"markText":"如果父母忽视、抹杀你真实的行为，重视的是全世界怎么看待你，那么，你最终将使用“外部记分卡”。而我的父亲——他是个百分之百的“内部记分卡”使用者。他是一位真正不随大流的独行者，但是，他并不是刻意为之。他只是不在乎他人的评价。我的父亲教会我应该怎样生活。我从未见过任何人能像他一样。","range":"4330-4500","createTime":1632055730,"type":1},{"bookId":"907585","bookmarkId":"907585_9_1561-1620","chapterUid":9,"markText":"对一家成熟、每年为投资者赚4亿美元的大型企业而言，应该支付多少钱呢？对一家新生、亏钱的小型企业，又应该支付什么价格呢？","range":"1565-1624","createTime":1632055597,"type":1},{"bookId":"907585","bookmarkId":"907585_8_6941-7269","chapterUid":8,"markText":"通过传真、邮递和电子邮件传给他的每日、每周以及月度报告，都是伯克希尔下属的公司给他的资料。业绩清单一年比一年长，巴菲特从清单上知道——上周GEICO（政府雇员保险公司）又卖出了多少份汽车保险，又偿付了多少索赔；昨天卖出了几磅喜诗糖果；范奇海默公司又拿到了多少件监狱看守制服的订单；奈特捷在欧洲和美国卖出了多少架分权喷气机。除此之外，还有——帆布篷、充电器、发电数（千瓦/时）、空气压缩机、订婚戒指、租赁卡车、百科全书、飞行员训练、家具装饰、心肺医疗仪器、猪圈、房地产经纪、圣代冰激凌、绞车和起锚机、天然气、污水深井泵、吸尘器、报纸广告、计卵器、刀具、家具租金、护士鞋、机电零件……所有关于成本、销售额的数据都涌进巴菲特的办公室，他记住了这当中非常多的数字。","range":"6941-7269","createTime":1632055431,"type":1},{"bookId":"907585","bookmarkId":"907585_8_5727-5748","chapterUid":8,"markText":"他的慈善都是达尔文式的，以激励最优秀的人。","range":"5727-5748","createTime":1632055326,"type":1},{"bookId":"907585","bookmarkId":"907585_7_27960-27994","chapterUid":7,"markText":"巴菲特显然对可以免费获取的信息置之不理，而且无视新世纪正到来的现实。","range":"27960-27994","createTime":1632054980,"type":1},{"bookId":"907585","bookmarkId":"907585_7_25877-25936","chapterUid":7,"markText":"不过，有些人认为他们听到了很重要的事情。“很了不起，这是关于股票市场的基础教程，一节课就涵盖了一切。”这是盖茨的想法。","range":"25877-25936","createTime":1632054861,"type":1},{"bookId":"907585","bookmarkId":"907585_7_21966-22035","chapterUid":7,"markText":"你预见到所有这些人要么希望坐着飞机走亲访友，要么希望离家远走高飞，或者你预见到了任何可以在飞机里做的事。然后，你决定这就是你要投资的领域。","range":"21966-22035","createTime":1632054628,"type":1},{"bookId":"907585","bookmarkId":"907585_7_20199-20233","chapterUid":7,"markText":"有些人并不认为整个市场会繁荣，他们只是认为自己能够从中挑选出胜利者。","range":"20199-20233","createTime":1632054515,"type":1},{"bookId":"907585","bookmarkId":"907585_7_19391-20165","chapterUid":7,"markText":"只有三种方式，股票可以保持一年10%或10%以上的增长。一是利率下降，保持在历史低位。二是投资者，而不是雇员、政府或其他主体，在经济中所占份额高于历史已有水平。[插图]他说，还有就是经济的增速开始快于正常情况。[插图]诸如此类的乐观假设被巴菲特斥为“痴心妄想”。","range":"19391-20165","createTime":1632054411,"type":1},{"bookId":"907585","bookmarkId":"907585_7_19240-19352","chapterUid":7,"markText":"他们的态度是，巴菲特没有资格说他们贪婪。巴菲特，这个聚敛钱财数年、几乎不往外拿的人，这个从车牌就能看出其“节约”的吝啬鬼，这个将大部分时间用于思考如何赚钱的人，这个打破IT泡沫、没搭乘IT列车的人，正在往他们的香槟里吐口水。","range":"19240-19352","createTime":1632054355,"type":1},{"bookId":"907585","bookmarkId":"907585_7_18784-18906","chapterUid":7,"markText":"利率——借贷成本——是对“时间”的定价。金融领域的利率就如同物理学当中的重力。利率变化，所有金融资产，包括房子、股票、债券的价值都会发生变化，就如同鸟的价值会波动一样。“这就是为什么有时手里的鸟比林子里的鸟值钱，有时林子里的鸟比手里的鸟值钱。”","range":"18784-18906","createTime":1632054280,"type":1},{"bookId":"907585","bookmarkId":"907585_7_18590-18675","chapterUid":7,"markText":"当你们投资的时候，你们所做的事情是延迟消费，现在把钱投出去，在一段时间之后会获得更多的钱。关于投资，只存在两个真正的问题：一是你想得到多少回报，二是你想什么时间得到回报。","range":"18590-18675","createTime":1632054255,"type":1},{"bookId":"907585","bookmarkId":"907585_7_15190-15279","chapterUid":7,"markText":"市场并不只是人们买卖股票的地方，股票似乎是赌场里的筹码，筹码则代表了公司业务。巴菲特思考的是筹码的总体价值。这些筹码值多少钱？然后，巴菲特会从源源不断的文件中评估公司以往的业绩。","range":"15190-15279","createTime":1632054012,"type":1},{"bookId":"907585","bookmarkId":"907585_7_13457-13526","chapterUid":7,"markText":"新闻记者们对互联网名人们紧追不放，往返于其居住的公寓和会场，这种场景放大了他们已经膨胀的自大情绪，这种情绪已经渗透到1999年太阳谷年会中","range":"13457-13526","createTime":1632053904,"type":1},{"bookId":"907585","bookmarkId":"907585_7_22066-22377","chapterUid":7,"markText":"历史上，对航空企业的所有股票投资都赚不到钱，和几年前的情形如出一辙。因此，我想告诉你们：我真的宁愿这么想——当我回到小鹰号时代，我会有足够的远见和“见义勇为”的精神，把奥维尔·莱特[插图]给打下来。但我没做到，我有愧于未来的资本投资人。[插图]","range":"22066-22376","createTime":1626520120,"type":1},{"bookId":"907585","bookmarkId":"907585_7_20426-20859","chapterUid":7,"markText":"汽车是20世纪上半叶最重大的发明。它对人们的生活产生了巨大的影响。如果你在第一批汽车诞生的时代目睹了国家是如何因为汽车而发展起来的，那么你可能会说，“这是我必须要投资的领域。”但是，在几十年前的2 000多家汽车企业中，只有3家企业活了下来。[插图]而且，曾几何时，这3家公司的出售价格都低于其账面价值，即低于当初投入公司并留存下来的资金数额。因此，虽然汽车对美国产生了巨大的正面影响，但却对投资者产生了相反的冲击。","range":"20426-20859","createTime":1626520063,"type":1}],"removed":[],"chapters":[{"title":"4 沃伦，你怎么了？","chapterUid":9,"chapterIdx":9},{"title":"2 太阳谷","chapterUid":7,"chapterIdx":7},{"title":"3 习惯性动物","chapterUid":8,"chapterIdx":8}],"book":{"bookId":"907585","version":1055036898,"format":"epub","soldout":0,"bookStatus":1,"cover":"https://cdn.weread.qq.com/weread/cover/86/YueWen_907585/s_YueWen_907585.jpg","title":"滚雪球：巴菲特和他的财富人生（套装共2册）","author":"艾丽斯·施罗德","coverBoxInfo":{"blurhash":"KnGu,mxu00IUj[xu4nRj-;","colors":[{"key":"1/4","hex":"#211b1d"},{"key":"1/6","hex":"#211b1d"},{"key":"1/8","hex":"#211b1d"},{"key":"2/4","hex":"#352f30"},{"key":"2/6","hex":"#352f30"},{"key":"2/8","hex":"#352f30"},{"key":"3/4","hex":"#4c4646"},{"key":"3/6","hex":"#4c4646"},{"key":"3/8","hex":"#4c4646"},{"key":"3/12","hex":"#4c4646"},{"key":"4/6","hex":"#655f5f"},{"key":"4/10","hex":"#655f5f"},{"key":"4/4","hex":"#655f5f"},{"key":"5/10","hex":"#7e7878"},{"key":"5/4","hex":"#7e7878"},{"key":"5/8","hex":"#7e7878"},{"key":"6/4","hex":"#979292"},{"key":"6/6","hex":"#979292"},{"key":"6/8","hex":"#979292"},{"key":"6/12","hex":"#979292"},{"key":"7/8","hex":"#b1acac"},{"key":"7/10","hex":"#b1acac"},{"key":"7/12","hex":"#b1acac"},{"key":"8/4","hex":"#cbc7c7"},{"key":"8/6","hex":"#cbc7c7"},{"key":"8/12","hex":"#cbc7c7"},{"key":"9/2","hex":"#e6e2e2"},{"key":"9/12","hex":"#e6e2e2"},{"key":"1/100","hex":"#979292"},{"key":"2/100","hex":"#b1acac"},{"key":"3/100","hex":"#ffffff"},{"key":"4/100","hex":"#EEEEEE"},{"key":"5/100","hex":"#EEEEEE"},{"key":"6/100","hex":"#000000"}],"dominate_color":{"hex":"#b0abab","hsv":[352.74681909783768,3.229537081531316,69.0954669229537]},"custom_cover":"https://weread-1258476243.file.myqcloud.com/bookalphacover/585/907585/s_907585.jpg","custom_rec_cover":"https://weread-1258476243.file.myqcloud.com/bookreccover/585/907585/s_907585.jpg","colorsPure":["#979292","#b1acac"]}}}