[
  {
    "bookId": "187809",
    "content": "这个有意思",
    "time": 1579590597,
    "chapterName": null,
    "star": null,
    "abstract": "在购物中心里，基本面的分析员会走进每家商店，仔细研究它们的商品，然后决定是否购买。相反的，技术分析员将会坐在购物中心的长椅上，观察商店的人流量。他们不关心商品的真正价值，只关注商店的人流量。”",
    "range": "591-687"
  },
  {
    "bookId": "21034166",
    "content": "怪怪的",
    "time": 1580183495,
    "chapterName": null,
    "star": null,
    "abstract": "赵先生",
    "range": "497-500"
  },
  {
    "bookId": "21133953",
    "content": "+1s",
    "time": 1583124437,
    "chapterName": null,
    "star": null,
    "abstract": "给国家泼脏水，将来宣传上出了偏差，你是要负责任的",
    "range": "852-876"
  },
  {
    "bookId": "21449273",
    "content": "短小无力吐槽",
    "time": 1580959166,
    "chapterName": null,
    "star": null,
    "abstract": "“电磁体研究实验室！”\r\n　　“他们罢工了！”",
    "range": "2732-2755"
  },
  {
    "bookId": "21449273",
    "content": "",
    "time": 1578101543,
    "chapterName": null,
    "star": 100,
    "abstract": null,
    "range": null
  },
  {
    "bookId": "21489683",
    "content": "会成为伏笔吗？",
    "time": 1572953665,
    "chapterName": null,
    "star": null,
    "abstract": "“交给我吧！这也是永昌留下的唯一的东西了，我想留作纪念！”",
    "range": "1144-1173"
  },
  {
    "bookId": "22615133",
    "content": "12%",
    "time": 1590906176,
    "chapterName": null,
    "star": null,
    "abstract": "对于一个成功的选股策略而言，首先要做的就是找到那些在将来许多年收入能持续增长的上市公司。长期来看，美股股价每年平均递增8%是司空见惯的事，原因在于许多上市公司的收入一般都能以年均8%的速度增长，而且它们还在支付3%的股息。",
    "range": "2005-2116"
  },
  {
    "bookId": "22716996",
    "content": "",
    "time": 1578033493,
    "chapterName": null,
    "star": 100,
    "abstract": null,
    "range": null
  },
  {
    "bookId": "23416117",
    "content": "从股市稳赚过来的，这本写的更通俗易懂，结论部分算半个广告，对价值投资的推论是最值得阅读的部分。神奇公式网是中文版操作平台，不了解的可以去看看。作者几本书的思路是清晰一以贯之的，是个有意思的大佬",
    "time": 1581172631,
    "chapterName": null,
    "star": 80,
    "abstract": "",
    "range": ""
  },
  {
    "bookId": "23416117",
    "content": "",
    "time": 1545470029,
    "chapterName": null,
    "star": 100,
    "abstract": "",
    "range": ""
  },
  {
    "bookId": "23514493",
    "content": "",
    "time": 1577633437,
    "chapterName": null,
    "star": 100,
    "abstract": "",
    "range": ""
  },
  {
    "bookId": "23570329",
    "content": "宁远到底是哪里",
    "time": 1580140637,
    "chapterName": null,
    "star": null,
    "abstract": "聚集发病区域……在云鹤的一个野味市场。”",
    "range": "2611-2631"
  },
  {
    "bookId": "23570329",
    "content": "武汉市湖北省",
    "time": 1579962774,
    "chapterName": null,
    "star": null,
    "abstract": "宁远市甚至宋安省，",
    "range": "1053-1062"
  },
  {
    "bookId": "23730282",
    "content": "没参加过高考吗？",
    "time": 1578101508,
    "chapterName": null,
    "star": null,
    "abstract": "由于今年的全国所有的大学录取分数线是历史上最低点，因此本年度的新生严重超标。",
    "range": "1517-1555"
  },
  {
    "bookId": "23768857",
    "content": "",
    "time": 1574403904,
    "chapterName": null,
    "star": 100,
    "abstract": "",
    "range": ""
  },
  {
    "bookId": "23784694",
    "content": "",
    "time": 1559537430,
    "chapterName": null,
    "star": 100,
    "abstract": "",
    "range": ""
  },
  {
    "bookId": "24265945",
    "content": "我觉得这个书有些偏激",
    "time": 1578273293,
    "chapterName": null,
    "star": null,
    "abstract": "中国文化的深层结构",
    "range": "1752-1761"
  },
  {
    "bookId": "24275777",
    "content": "",
    "time": 1745277594,
    "chapterName": null,
    "star": 100,
    "abstract": "",
    "range": ""
  },
  {
    "bookId": "25023817",
    "content": "",
    "time": 1574403924,
    "chapterName": null,
    "star": 100,
    "abstract": "",
    "range": ""
  },
  {
    "bookId": "25615643",
    "content": "这种家庭吃这个？",
    "time": 1581323344,
    "chapterName": null,
    "star": null,
    "abstract": "红烧牛肉、回锅肉、青椒肉丝、麻婆豆腐、西红柿鸡蛋汤。”",
    "range": "2146-2173"
  },
  {
    "bookId": "25623497",
    "content": "没花钱就得到的就是服务",
    "time": 1606030867,
    "chapterName": null,
    "star": null,
    "abstract": "为什么你在享受这些服务的时候不用付钱，而这些服务的提供商还乐此不疲地为你提供最优质的服务呢？答案依然是经济金融的逻辑在起作用。",
    "range": "1062-1125"
  },
  {
    "bookId": "25623497",
    "content": "",
    "time": 1606030784,
    "chapterName": null,
    "star": 100,
    "abstract": "",
    "range": ""
  },
  {
    "bookId": "25623499",
    "content": "",
    "time": 1573118364,
    "chapterName": null,
    "star": 100,
    "abstract": "",
    "range": ""
  },
  {
    "bookId": "25812723",
    "content": "",
    "time": 1561500666,
    "chapterName": null,
    "star": 100,
    "abstract": "",
    "range": ""
  },
  {
    "bookId": "25886579",
    "content": "引导思维推理",
    "time": 1586668105,
    "chapterName": null,
    "star": null,
    "abstract": "只要能够诱导人们不对别人进行人身攻击，也不侵犯他人财产，然后派生出工业、农业、知识和艺术的那些积极协作，就会自然而然地发展起来。但会这样吗？又为什么该是这样呢？",
    "range": "1010-1090"
  },
  {
    "bookId": "26244219",
    "content": "😃",
    "time": 1583109261,
    "chapterName": null,
    "star": null,
    "abstract": "直接从索罗斯本人那里得到了求证",
    "range": "1017-1032"
  },
  {
    "bookId": "26356172",
    "content": "2019年穿过去的！！！",
    "time": 1578837810,
    "chapterName": null,
    "star": null,
    "abstract": "“看到它们，便心情舒适，觉得自己富可敌国",
    "range": "740-760"
  },
  {
    "bookId": "26356172",
    "content": "AE86 就是快",
    "time": 1578616921,
    "chapterName": null,
    "star": null,
    "abstract": "“良人，好疼。”",
    "range": "0-8"
  },
  {
    "bookId": "26356172",
    "content": "",
    "time": 1578616001,
    "chapterName": null,
    "star": 100,
    "abstract": null,
    "range": null
  },
  {
    "bookId": "26392814",
    "content": "股价影响业绩的情况下是对的。",
    "time": 1588554253,
    "chapterName": null,
    "star": null,
    "abstract": "公司的总裁为了能坐稳位置，第一要务是保证股价稳定，否则不管你有什么抱负、愿景，一旦股价下跌了，很可能就出师未捷身先死了。",
    "range": "18578-18638"
  },
  {
    "bookId": "26392814",
    "content": "美国用的是全世界的智力资源。民智？笑笑。。",
    "time": 1588521589,
    "chapterName": null,
    "star": null,
    "abstract": "只有整个国家的民智被开启了，创新文化才能出现。",
    "range": "8423-8446"
  },
  {
    "bookId": "26392814",
    "content": "喜欢这个思考",
    "time": 1588518718,
    "chapterName": null,
    "star": null,
    "abstract": "个人投资者就需要重新考虑：是不是好的方法就是适合自己的方法？我们需要的是以一种更简单、直观的方式去发现有价值的公司。而这个答案，依旧要从历史中去获取。",
    "range": "6357-6432"
  },
  {
    "bookId": "26392814",
    "content": "大分流以来，解释框架里有力的一种，为什么股票大于债券黄金和现金，因为经济螺旋上升，这背后的答案就是科技加市场经济制度。",
    "time": 1588516549,
    "chapterName": null,
    "star": null,
    "abstract": "是否看好一个国家未来的股市，预期一下这个国家是否以民主、法制治国，是否坚持市场经济的理念，其实就会得出一个大概的结论。",
    "range": "2486-2545"
  },
  {
    "bookId": "26392814",
    "content": "切换到宏观历史视角",
    "time": 1588516161,
    "chapterName": null,
    "star": null,
    "abstract": "当时的荷兰并不是海洋贸易最发达的国家。比它资格更老的有葡萄牙、西班牙，葡萄牙基本上垄断了非洲、亚洲的航线贸易，西班牙则基本掌控了美洲航线。荷兰当时只是经营欧洲本身的贸易，把西班牙从美洲获取的黄金，以及葡萄牙从印度获取的香料在欧洲买卖，可以说只是一个中间商的身份。那么为什么股票没有在葡萄牙、西班牙诞生，偏偏在荷兰产生了呢？实际上不仅是股票，甚至是现代的银行业、期货、期权之后都相继在荷兰产生，在荷兰这个弹丸之地，一个国家就把现代世界的金融雏形建立起来，这里面是有更深层次的原因的。",
    "range": "1422-1662"
  },
  {
    "bookId": "26392814",
    "content": "可以半跪上帝、女王，但对你异域皇帝不行，这样的自信，或者说傲慢来源的时间和事件在哪里？",
    "time": 1588516080,
    "chapterName": null,
    "star": null,
    "abstract": "你要找皇帝谈判，首先得低头屈膝，这一点欧洲人普遍不能接受，所以欧洲与中国的贸易就一直卡在开头没有任何进展。",
    "range": "2143-2196"
  },
  {
    "bookId": "26392814",
    "content": "？？？",
    "time": 1588515523,
    "chapterName": null,
    "star": null,
    "abstract": "德高望重的股评家",
    "range": "22321-22329"
  },
  {
    "bookId": "26392814",
    "content": "？？？\n想表达什么",
    "time": 1588514161,
    "chapterName": null,
    "star": null,
    "abstract": "要知道现存的百年企业及其家族，没有一个是依靠股市发家致富的；",
    "range": "1799-1829"
  },
  {
    "bookId": "26427988",
    "content": "？？？剑指队",
    "time": 1580979489,
    "chapterName": null,
    "star": null,
    "abstract": "剑指S...咳咳...",
    "range": "1463-1474"
  },
  {
    "bookId": "26454342",
    "content": "2020.9.11",
    "time": 1599782620,
    "chapterName": null,
    "star": null,
    "abstract": "新时代的投资方法转而将盈利趋势作为价值判断的唯一标准。这种方法虽然可能存在某种程度的合理性，但其在摒弃计算过程以及约束的条件下盲目择股，必将导致可怕的市场崩溃。",
    "range": "459-539"
  },
  {
    "bookId": "26528093",
    "content": "这武汉大学咋考的",
    "time": 1579211016,
    "chapterName": null,
    "star": null,
    "abstract": "听见了，但听不懂啊",
    "range": "345-354"
  },
  {
    "bookId": "26528093",
    "content": "20岁算大了吧",
    "time": 1579172217,
    "chapterName": null,
    "star": null,
    "abstract": "小明之前一直是俱乐部里最小的选手，现在，终于来个比他小的了！",
    "range": "2062-2092"
  },
  {
    "bookId": "26640431",
    "content": "不精确啊？",
    "time": 1572613904,
    "chapterName": null,
    "star": null,
    "abstract": "十多个方法",
    "range": "4594-4599"
  },
  {
    "bookId": "26689021",
    "content": "哈哈哈哈",
    "time": 1593076844,
    "chapterName": null,
    "star": null,
    "abstract": "不时闪现出的迷茫而又无辜的眼神，深深地打动了他。",
    "range": "2885-2909"
  },
  {
    "bookId": "26923630",
    "content": "不装了，我摊牌了。",
    "time": 1595769663,
    "chapterName": null,
    "star": null,
    "abstract": "自然，简单说就是不装。人一不装，就生动了，就有趣了。生动就是没有条条框框，不死板，顺应自然，该说说，该笑笑。有趣就是展现出自己的真实面貌、真实性情、真实喜好。",
    "range": "732-811"
  },
  {
    "bookId": "27256052",
    "content": "五星佳作",
    "time": 1576276998,
    "chapterName": null,
    "star": 100,
    "abstract": "",
    "range": ""
  },
  {
    "bookId": "27328448",
    "content": "意义",
    "time": 1649592255,
    "chapterName": null,
    "star": null,
    "abstract": "营造氛围让圣诞节、元旦、复活节显得更快乐、更隆重一样，生活中的“平常事”减少了，你的生活就会增添几分魅力。",
    "range": "1666-1719"
  },
  {
    "bookId": "27444806",
    "content": "车技可以",
    "time": 1601857978,
    "chapterName": null,
    "star": null,
    "abstract": "王大春打了一个，从出生到现在，从未如此舒爽过的哆嗦，直接昏了过去。",
    "range": "702-735"
  },
  {
    "bookId": "27571559",
    "content": "高等级链接",
    "time": 1583115775,
    "chapterName": null,
    "star": null,
    "abstract": "",
    "range": ""
  },
  {
    "bookId": "277542",
    "content": "想想中国呢",
    "time": 1588119366,
    "chapterName": null,
    "star": null,
    "abstract": "正是这种文化优越感导致美国媒体揪着新加坡不放，指责我们是威权主义、专制主义，说新加坡社会是一个管理过严、约束过多、令人窒息、缺乏生机的社会。为什么呢？因为我们没有遵循美国的社会管理理念。但我们不能让其他人拿我们新加坡人的社会搞试验，万一失败，我们承担不起后果。他们的理念都是理论，都是没有经过证实的理论，没有在东亚得到证实，甚至没有在菲律宾得到证实，要知道，美国殖民统治菲律宾长达50年。",
    "range": "2123-2317"
  },
  {
    "bookId": "277542",
    "content": "问题在哪里？",
    "time": 1588118673,
    "chapterName": null,
    "star": null,
    "abstract": "中国告诉我们，国家无论大小，都是平等的，中国不是霸权国家。但是，当我们做了中国不喜欢的事，他们就说你让13亿人不高兴了……所以，请搞清楚你的位置。",
    "range": "1704-1777"
  },
  {
    "bookId": "28064625",
    "content": "还有这好事",
    "time": 1628896675,
    "chapterName": null,
    "star": null,
    "abstract": "再熬两个月看看吧，实在不行就回学校教书了",
    "range": "1720-1740"
  },
  {
    "bookId": "29375557",
    "content": "训练有素",
    "time": 1594442039,
    "chapterName": null,
    "star": null,
    "abstract": "鲁清顿时笑容满面。\r\n　　必须保质保量的完成小老弟得要求！",
    "range": "1831-1860"
  },
  {
    "bookId": "3000001768",
    "content": "",
    "time": 1560410314,
    "chapterName": null,
    "star": 100,
    "abstract": "",
    "range": ""
  },
  {
    "bookId": "3000007354",
    "content": "",
    "time": 1563142388,
    "chapterName": null,
    "star": 100,
    "abstract": "",
    "range": ""
  },
  {
    "bookId": "3000010649",
    "content": "",
    "time": 1564479129,
    "chapterName": null,
    "star": 100,
    "abstract": "",
    "range": ""
  },
  {
    "bookId": "3000013636",
    "content": "",
    "time": 1563045733,
    "chapterName": null,
    "star": 100,
    "abstract": "",
    "range": ""
  },
  {
    "bookId": "3000014851",
    "content": "",
    "time": 1564489844,
    "chapterName": null,
    "star": 100,
    "abstract": "",
    "range": ""
  },
  {
    "bookId": "3000014954",
    "content": "",
    "time": 1565875333,
    "chapterName": null,
    "star": 100,
    "abstract": "",
    "range": ""
  },
  {
    "bookId": "3000023035",
    "content": "",
    "time": 1562808041,
    "chapterName": null,
    "star": 100,
    "abstract": "",
    "range": ""
  },
  {
    "bookId": "3000026487",
    "content": "",
    "time": 1566203125,
    "chapterName": null,
    "star": 100,
    "abstract": "",
    "range": ""
  },
  {
    "bookId": "3000026697",
    "content": "",
    "time": 1567199454,
    "chapterName": null,
    "star": 100,
    "abstract": "",
    "range": ""
  },
  {
    "bookId": "3000027040",
    "content": "",
    "time": 1574336066,
    "chapterName": null,
    "star": 100,
    "abstract": "",
    "range": ""
  },
  {
    "bookId": "3000027880",
    "content": "",
    "time": 1609993952,
    "chapterName": null,
    "star": 100,
    "abstract": "",
    "range": ""
  },
  {
    "bookId": "3000030259",
    "content": "想读",
    "time": 1560515733,
    "chapterName": null,
    "star": 100,
    "abstract": "",
    "range": ""
  },
  {
    "bookId": "3000034239",
    "content": "",
    "time": 1564365462,
    "chapterName": null,
    "star": 100,
    "abstract": "",
    "range": ""
  },
  {
    "bookId": "3000037548",
    "content": "",
    "time": 1569830814,
    "chapterName": null,
    "star": 100,
    "abstract": "",
    "range": ""
  },
  {
    "bookId": "3000046569",
    "content": "期待",
    "time": 1560722431,
    "chapterName": null,
    "star": 100,
    "abstract": "",
    "range": ""
  },
  {
    "bookId": "3000055100",
    "content": "",
    "time": 1566640574,
    "chapterName": null,
    "star": 100,
    "abstract": "",
    "range": ""
  },
  {
    "bookId": "3000055100",
    "content": "",
    "time": 1561421022,
    "chapterName": null,
    "star": 100,
    "abstract": "",
    "range": ""
  },
  {
    "bookId": "3000056645",
    "content": "",
    "time": 1564732890,
    "chapterName": null,
    "star": 100,
    "abstract": "",
    "range": ""
  },
  {
    "bookId": "3000061827",
    "content": "",
    "time": 1574079933,
    "chapterName": null,
    "star": 100,
    "abstract": "",
    "range": ""
  },
  {
    "bookId": "3000062700",
    "content": "",
    "time": 1552740316,
    "chapterName": null,
    "star": 100,
    "abstract": "",
    "range": ""
  },
  {
    "bookId": "3000083292",
    "content": "",
    "time": 1568176221,
    "chapterName": null,
    "star": 100,
    "abstract": "",
    "range": ""
  },
  {
    "bookId": "3000093835",
    "content": "",
    "time": 1575070672,
    "chapterName": null,
    "star": 100,
    "abstract": "",
    "range": ""
  },
  {
    "bookId": "3000094286",
    "content": "",
    "time": 1567084956,
    "chapterName": null,
    "star": 100,
    "abstract": "",
    "range": ""
  },
  {
    "bookId": "3000097718",
    "content": "",
    "time": 1559647603,
    "chapterName": null,
    "star": 100,
    "abstract": "",
    "range": ""
  },
  {
    "bookId": "3000102477",
    "content": "",
    "time": 1566394574,
    "chapterName": null,
    "star": 100,
    "abstract": "",
    "range": ""
  },
  {
    "bookId": "3000125547",
    "content": "",
    "time": 1566640552,
    "chapterName": null,
    "star": 100,
    "abstract": "",
    "range": ""
  },
  {
    "bookId": "3000125547",
    "content": "",
    "time": 1561628568,
    "chapterName": null,
    "star": 100,
    "abstract": "",
    "range": ""
  },
  {
    "bookId": "3000159479",
    "content": "",
    "time": 1566104271,
    "chapterName": null,
    "star": 100,
    "abstract": "",
    "range": ""
  },
  {
    "bookId": "3000160180",
    "content": "",
    "time": 1573303149,
    "chapterName": null,
    "star": 100,
    "abstract": "",
    "range": ""
  },
  {
    "bookId": "3000192436",
    "content": "",
    "time": 1569830830,
    "chapterName": null,
    "star": 100,
    "abstract": "",
    "range": ""
  },
  {
    "bookId": "3000193893",
    "content": "",
    "time": 1570151616,
    "chapterName": null,
    "star": 100,
    "abstract": "",
    "range": ""
  },
  {
    "bookId": "3000270585",
    "content": "",
    "time": 1573207904,
    "chapterName": null,
    "star": 100,
    "abstract": "",
    "range": ""
  },
  {
    "bookId": "3000275490",
    "content": "",
    "time": 1568092646,
    "chapterName": null,
    "star": 100,
    "abstract": "",
    "range": ""
  },
  {
    "bookId": "3000356218",
    "content": "",
    "time": 1567427803,
    "chapterName": null,
    "star": 100,
    "abstract": "",
    "range": ""
  },
  {
    "bookId": "3000543470",
    "content": "",
    "time": 1566999224,
    "chapterName": null,
    "star": 100,
    "abstract": "",
    "range": ""
  },
  {
    "bookId": "3000588085",
    "content": "",
    "time": 1566628263,
    "chapterName": null,
    "star": 100,
    "abstract": "",
    "range": ""
  },
  {
    "bookId": "3000622439",
    "content": "",
    "time": 1574086385,
    "chapterName": null,
    "star": 100,
    "abstract": "",
    "range": ""
  },
  {
    "bookId": "3001238097",
    "content": "",
    "time": 1620099887,
    "chapterName": null,
    "star": 100,
    "abstract": "",
    "range": ""
  },
  {
    "bookId": "3001261003",
    "content": "",
    "time": 1620223425,
    "chapterName": null,
    "star": 100,
    "abstract": "",
    "range": ""
  },
  {
    "bookId": "3001261187",
    "content": "",
    "time": 1569576221,
    "chapterName": null,
    "star": 100,
    "abstract": "",
    "range": ""
  },
  {
    "bookId": "3001627962",
    "content": "",
    "time": 1563509936,
    "chapterName": null,
    "star": 100,
    "abstract": "",
    "range": ""
  },
  {
    "bookId": "3002380005",
    "content": "",
    "time": 1565999139,
    "chapterName": null,
    "star": 100,
    "abstract": "",
    "range": ""
  },
  {
    "bookId": "30040471",
    "content": "任何情况都不应该忽视的环节，持有人角度，生意的所有人。",
    "time": 1587903017,
    "chapterName": null,
    "star": null,
    "abstract": "管理者持股的比例越高，他们的利益就越有可能与少数股东保持一致，这一环节在任何情况下都不应该被忽视。",
    "range": "12580-12629"
  },
  {
    "bookId": "30040471",
    "content": "个人投资和组合管理同理",
    "time": 1587687221,
    "chapterName": null,
    "star": null,
    "abstract": "重要的是，要避免为了增长而增长的冲动，投资重点应该放在有意义的收购上，而不是超额支付。避免用劣质收购削弱优质公司是很重要的。",
    "range": "11327-11389"
  },
  {
    "bookId": "30040471",
    "content": "起作用的力量",
    "time": 1587514969,
    "chapterName": null,
    "star": null,
    "abstract": "由于格雷厄姆的教导，基于人们对市场中起作用的力量的广泛分析，投资现在已经成为一项严肃而苛刻的技能。",
    "range": "1179-1228"
  },
  {
    "bookId": "30040486",
    "content": "王健林，许家印。。",
    "time": 1586391864,
    "chapterName": null,
    "star": null,
    "abstract": "精英群体中，工作时长跟社会地位紧密相关。超级富豪疯狂工作并且四处宣传，以证明他们社会地位的优越性。",
    "range": "969-1018"
  },
  {
    "bookId": "30040486",
    "content": "一天工作4-6个小时",
    "time": 1586391844,
    "chapterName": null,
    "star": null,
    "abstract": "每周工作21~30小时的人的幸福感和意义感都是最高的，而随着工作小时数的增加，烦恼也就开始增加了，这其中没有性别差异。",
    "range": "1081-1140"
  },
  {
    "bookId": "30214790",
    "content": "想啥呢？",
    "time": 1599286659,
    "chapterName": null,
    "star": null,
    "abstract": "或许可以招聘一个团队，潜心研发一两年，抢在鹅厂之前发布，不说达到对方的火爆程度，打两个对折，挣个一两亿，应该是问题不大。",
    "range": "2267-2327"
  },
  {
    "bookId": "30580616",
    "content": "这是啥朋友啊",
    "time": 1596941743,
    "chapterName": null,
    "star": null,
    "abstract": "李慕已经感受到身体发生了微妙的变化，他正要再次开口，张山急忙摆了摆手，他面色苍白，扶着墙，有气无力的开口。",
    "range": "3025-3078"
  },
  {
    "bookId": "30765451",
    "content": "第一支股票，从10万到100万又是那些股票，为什么买了就赚钱？",
    "time": 1593255874,
    "chapterName": null,
    "star": null,
    "abstract": "1961年，我们以均价28美元的成本控股了Dempster, Dempster当时的管理层资产利用效率比较低，所以我们更换了管理层。",
    "range": "10233-10299"
  },
  {
    "bookId": "30765451",
    "content": "资产软，负债硬，现金为王。",
    "time": 1593252600,
    "chapterName": null,
    "star": null,
    "abstract": "我们估算清算价值的第一条原则是，负债是真实的，但对于资产的价值必须持怀疑态度。",
    "range": "6637-6680"
  },
  {
    "bookId": "30765451",
    "content": "现金有100%清算价值，如果大街上是其他资产呢？",
    "time": 1593174886,
    "chapterName": null,
    "star": null,
    "abstract": "有效市场理论是错误的，市场价格经常会偏离内在价值。",
    "range": "883-908"
  },
  {
    "bookId": "30765451",
    "content": "没有涨跌幅，波动区间就会有很多的交易机会，也会被价值投资者抓到非理性的价格。",
    "time": 1593174727,
    "chapterName": null,
    "star": null,
    "abstract": "1933年以15美元买入马克卡车的股票，依然可以获利丰厚，这就是安全边际的力量。",
    "range": "3838-3878"
  },
  {
    "bookId": "30987780",
    "content": "有多少现在还跪着的人",
    "time": 1590502739,
    "chapterName": null,
    "star": null,
    "abstract": "我的解读将从亚当·斯密开始。他出生的前一年，清朝的雍正皇帝登基。《国富论》在伦敦刊印发行的同时，托马斯·杰斐逊在费城起草发表了《独立宣言》，历史在这种大跨度的勾连中散发出迷人的气息。",
    "range": "1806-1897"
  },
  {
    "bookId": "31170980",
    "content": "单位成本不一样",
    "time": 1591656621,
    "chapterName": null,
    "star": null,
    "abstract": "你制造的第10辆车的成本与第1 000辆车相同。对于主导几乎整个20世纪世界经济的其他事物，包括农产品和实物财产，情况皆是如此。",
    "range": "1077-1141"
  },
  {
    "bookId": "32490792",
    "content": "很一般",
    "time": 1600124182,
    "chapterName": null,
    "star": 20,
    "abstract": "",
    "range": ""
  },
  {
    "bookId": "32514595",
    "content": "呃。。。",
    "time": 1598962272,
    "chapterName": null,
    "star": null,
    "abstract": "",
    "range": ""
  },
  {
    "bookId": "32858372",
    "content": "一般",
    "time": 1601387185,
    "chapterName": null,
    "star": 20,
    "abstract": "",
    "range": ""
  },
  {
    "bookId": "3300031519",
    "content": "",
    "time": 1561502327,
    "chapterName": null,
    "star": 100,
    "abstract": "",
    "range": ""
  },
  {
    "bookId": "3300034511",
    "content": "女性的竞争？",
    "time": 1674298331,
    "chapterName": null,
    "star": null,
    "abstract": "女性势必会进化出对拥有资源的男性的偏好。但是，女性需要线索来指示男性拥有资源的情况。这些线索可能是间接的，比如一个男性的人格特征暗示他向社会上层流动的可能性。这些线索也可能是身体上的，比如一个男性的运动能力或健康状况。这些线索还可能包括名声方面的信息，比如一个男性在同辈人中获得的尊重。然而，经济资源提供了最直接的线索。",
    "range": "6750-6910"
  },
  {
    "bookId": "3300060215",
    "content": "",
    "time": 1569841311,
    "chapterName": null,
    "star": 100,
    "abstract": "",
    "range": ""
  },
  {
    "bookId": "3300064766",
    "content": "先看目标",
    "time": 1707045237,
    "chapterName": "明确使命 服务客户需求，助力业务发展",
    "star": null,
    "abstract": "使命是一切销售行为的基础，将影响组织及个人后续行为的统一。",
    "range": "440-469"
  },
  {
    "bookId": "3300079998",
    "content": "",
    "time": 1568713780,
    "chapterName": null,
    "star": 100,
    "abstract": "",
    "range": ""
  },
  {
    "bookId": "33028875",
    "content": "新奇的体验",
    "time": 1610496923,
    "chapterName": null,
    "star": 100,
    "abstract": "",
    "range": ""
  },
  {
    "bookId": "33064753",
    "content": "看看",
    "time": 1722160098,
    "chapterName": null,
    "star": 100,
    "abstract": "",
    "range": ""
  },
  {
    "bookId": "33215696",
    "content": "怪怪地",
    "time": 1608947032,
    "chapterName": null,
    "star": null,
    "abstract": "说罢她紧闭双眼，不再关注夏凡的动作，仿佛接下去任由他施为。",
    "range": "2336-2365"
  },
  {
    "bookId": "33831273",
    "content": "塑造口碑，加大宣传",
    "time": 1603530253,
    "chapterName": null,
    "star": null,
    "abstract": "时刻把握超预期价值的传递，力求通过产品的使用体验和极致服务去塑造正面口碑，实现增长。",
    "range": "6778-6820"
  },
  {
    "bookId": "34156605",
    "content": "",
    "time": 1568478451,
    "chapterName": null,
    "star": 100,
    "abstract": "",
    "range": ""
  },
  {
    "bookId": "34667605",
    "content": "挺系统的一本销售介绍书",
    "time": 1664935136,
    "chapterName": null,
    "star": 100,
    "abstract": "",
    "range": ""
  },
  {
    "bookId": "35036370",
    "content": "做大管家，要帮同事看到这个问题",
    "time": 1618645485,
    "chapterName": null,
    "star": null,
    "abstract": "在宣布了每个月的月目标之后，我会让员工在周报中，将本周的个人工作目标从月目标中分解出来，并按照这个目标，逐条填写了工作计划。通过这一举动，员工了解到自己在什么时候该做什么事情，便有了清晰的前进方向。",
    "range": "24881-24980"
  },
  {
    "bookId": "35866774",
    "content": "赵总",
    "time": 1630204358,
    "chapterName": null,
    "star": null,
    "abstract": "我是贝泽高中的二把手",
    "range": "1673-1683"
  },
  {
    "bookId": "35990049",
    "content": "青钢影？剑姬？",
    "time": 1625702204,
    "chapterName": null,
    "star": null,
    "abstract": "剑术与屠宰的差别，便在于精准与否",
    "range": "30-46"
  },
  {
    "bookId": "35990049",
    "content": "老lck荣光了",
    "time": 1625702036,
    "chapterName": null,
    "star": null,
    "abstract": "我辈义不容辞",
    "range": "1368-1374"
  },
  {
    "bookId": "36927973",
    "content": "",
    "time": 1609322900,
    "chapterName": null,
    "star": 100,
    "abstract": "",
    "range": ""
  },
  {
    "bookId": "37188205",
    "content": "大威天龙，大罗法咒",
    "time": 1627794125,
    "chapterName": null,
    "star": null,
    "abstract": "孽畜，我要你助我修行！”",
    "range": "1022-1034"
  },
  {
    "bookId": "37595152",
    "content": "一般",
    "time": 1620114977,
    "chapterName": null,
    "star": 20,
    "abstract": "",
    "range": ""
  },
  {
    "bookId": "37651057",
    "content": "",
    "time": 1565856393,
    "chapterName": null,
    "star": 100,
    "abstract": "",
    "range": ""
  },
  {
    "bookId": "38259842",
    "content": "可以看看",
    "time": 1721225768,
    "chapterName": null,
    "star": 100,
    "abstract": "",
    "range": ""
  },
  {
    "bookId": "38469789",
    "content": "？？",
    "time": 1628425771,
    "chapterName": null,
    "star": null,
    "abstract": "罗翔",
    "range": "391-393"
  },
  {
    "bookId": "39336334",
    "content": "",
    "time": 1629073300,
    "chapterName": null,
    "star": 100,
    "abstract": "",
    "range": ""
  },
  {
    "bookId": "39481985",
    "content": "笑死了，第九条",
    "time": 1649041446,
    "chapterName": null,
    "star": null,
    "abstract": "分手带给我的好处：\n1. 我前任的家在蒙大拿，我现在不用操心必须搬到他家附近要考虑的问题了；\n2. 不用再为谁洗碗而争吵了；\n3. 有更多的时间和我的朋友们相聚了，我的前任不把他们当回事；\n4. 因为不住在前任的公寓了，所以上下班的路程更短了；\n5. 不用再穿着沾有狗毛的衣服上班了；\n6. 不用在劳动节的周末去参加花费不菲的婚礼了；\n7. 可以花更多的时间在音乐上；\n8. 我的前任讨厌我弟弟，我不必再为和弟弟在一起找借口了；\n9. 不必假装喜欢看《美国白马王子》了；\n10. 有机会找到一段幸福、健康的亲密关系。",
    "range": "3351-3889"
  },
  {
    "bookId": "40055543",
    "content": "",
    "time": 1628917974,
    "chapterName": null,
    "star": 100,
    "abstract": "",
    "range": ""
  },
  {
    "bookId": "41170822",
    "content": "您就是数学荣光哥了",
    "time": 1644116067,
    "chapterName": null,
    "star": null,
    "abstract": "我相信我能有现在的选择权，金手指功不可没，重铸体育荣光，吾辈义不容辞。",
    "range": "339-374"
  },
  {
    "bookId": "41170822",
    "content": "陆舟！！",
    "time": 1644113778,
    "chapterName": null,
    "star": null,
    "abstract": "舟字前辈钻研数学七大猜想的感觉",
    "range": "12-27"
  },
  {
    "bookId": "42969530",
    "content": "哦哦，好的👌",
    "time": 1662815610,
    "chapterName": null,
    "star": null,
    "abstract": "薄南客",
    "range": "148-151"
  },
  {
    "bookId": "43346986",
    "content": "",
    "time": 1560651343,
    "chapterName": null,
    "star": 100,
    "abstract": "",
    "range": ""
  },
  {
    "bookId": "43833616",
    "content": "懂了吧",
    "time": 1657410383,
    "chapterName": null,
    "star": null,
    "abstract": "LPL已经拿到四次世界冠军了。\r\n　　登峰造极、凤凰涅槃、不破不立、虚空来袭。",
    "range": "683-722"
  },
  {
    "bookId": "45317617",
    "content": "哈哈哈哈哈",
    "time": 1677801911,
    "chapterName": "等死，纵火焚粮可乎？",
    "star": null,
    "abstract": "临死前，他挣扎着爬向自己的手机，将其格式化后才彻底失去意识。\r\n　　粉身碎骨浑不怕，要留清白在人间！",
    "range": "2104-2154"
  },
  {
    "bookId": "462592",
    "content": "",
    "time": 1577409951,
    "chapterName": null,
    "star": 100,
    "abstract": "",
    "range": ""
  },
  {
    "bookId": "462592",
    "content": "可以啊",
    "time": 1577270745,
    "chapterName": null,
    "star": null,
    "abstract": "今天来剑庐，他当然不敢带着影子，那个身影是谁？如果是四顾剑，为什么自己会觉得熟悉？\r\n",
    "range": "3462-3503"
  },
  {
    "bookId": "462592",
    "content": "他不是没有参加考试吗？？？",
    "time": 1577070884,
    "chapterName": null,
    "star": null,
    "abstract": "御史贺宗纬",
    "range": "536-541"
  },
  {
    "bookId": "496740",
    "content": "都知道是谁",
    "time": 1577667783,
    "chapterName": null,
    "star": null,
    "abstract": "一个长得很奇葩的企业家，不仅私自转移企业的核心业务，而且还公然撕破先前和风投签下的协议，给海外投资机构留下一个极坏的印象，后来此人把自己包装成一个人生导师，整天在社交媒体上发表“心灵鸡汤”，以此来满足自己前几十年的落寞，最后此人竟然狂妄到公然对国家大事评头论足，站到了绝大多数有正义、有良知的人的对立面。",
    "range": "3126-3278"
  },
  {
    "bookId": "602775",
    "content": "A1？",
    "time": 1591880783,
    "chapterName": null,
    "star": null,
    "abstract": "云南白药（000538）、张裕A（000869）每年公司净利润增长幅度较大且十分稳定，已经被市场给予高估值并被追求稳定性收益的资金锁仓。",
    "range": "3730-3798"
  },
  {
    "bookId": "602775",
    "content": "也就意味着一半的股票是B2",
    "time": 1591880756,
    "chapterName": null,
    "star": null,
    "abstract": "三快的个股基本上是游资做的盘面。由于游资的存在，很多个股股价是无法用基本面分析的，这类个股占整个市场股票数量的一半以上。",
    "range": "3967-4076"
  },
  {
    "bookId": "603257",
    "content": "",
    "time": 1573377489,
    "chapterName": null,
    "star": 100,
    "abstract": "",
    "range": ""
  },
  {
    "bookId": "621949",
    "content": "有哪些？会计逻辑",
    "time": 1582980245,
    "chapterName": null,
    "star": null,
    "abstract": "通过会计专业知识，找出公司的财务报表上能够暴露企业经营不稳定问题的地方。",
    "range": "1428-1464"
  },
  {
    "bookId": "621949",
    "content": "想想视觉中国的获客手段，客户的依赖、信任不会坚固，以后会出问题的。",
    "time": 1582973629,
    "chapterName": null,
    "star": null,
    "abstract": "可持续的商业模式是以公司的经营原则为基础，尤其是那些与资本监管、责任、坦诚相关的原则。",
    "range": "956-999"
  },
  {
    "bookId": "635838",
    "content": "直到供大于求",
    "time": 1612781077,
    "chapterName": null,
    "star": null,
    "abstract": "索维尔解释道，这些价格并没有什么不公平之处，它们只是反映出购买者和销售者在他们交换的物品上所同意的价值。",
    "range": "3534-3586"
  },
  {
    "bookId": "635881",
    "content": "不是2001？",
    "time": 1581039674,
    "chapterName": null,
    "star": null,
    "abstract": "2012年11月16日，",
    "range": "1067-1079"
  },
  {
    "bookId": "709279",
    "content": "？？？",
    "time": 1581596677,
    "chapterName": null,
    "star": null,
    "abstract": "1984年，邓公南巡",
    "range": "2392-2402"
  },
  {
    "bookId": "713349",
    "content": "我们生命的优先级是什么？",
    "time": 1577428697,
    "chapterName": null,
    "star": null,
    "abstract": "人们把大部分精力都花在追求快乐上，但对快乐的态度却是既复杂又矛盾。快乐是人类生活的巨大驱动力，为了生存并将我们的基因遗传给下一代，人们首先必须解决食物、水和性的问题。某些形式的快乐只在特定的场合发生，比如在重要的宗教仪式中，祷告、音乐、舞蹈以及冥想所带来的超验的快乐感受，已经成为人类文化生活中不可或缺的一部分。",
    "range": "1622-1778"
  },
  {
    "bookId": "716490",
    "content": "",
    "time": 1583162872,
    "chapterName": null,
    "star": 100,
    "abstract": "",
    "range": ""
  },
  {
    "bookId": "716490",
    "content": "格雷厄姆中国版简化的特色",
    "time": 1583160776,
    "chapterName": null,
    "star": null,
    "abstract": "最首要的企业盈利情况不考虑，那资产负债表和分红这些基本建立在企业经营基础之上的东西还有必要考虑吗？",
    "range": "3685-3734"
  },
  {
    "bookId": "716490",
    "content": "特别是转化成现金流的能力",
    "time": 1583159572,
    "chapterName": null,
    "star": null,
    "abstract": "能将“对的事做对”的主体，寻找那种可以给予较高置信区间、能够将良好的商业预期成功转变为为巩固的差异化竞争优势和现金流的有战斗力的组织。",
    "range": "322-389"
  },
  {
    "bookId": "716490",
    "content": "抵制诱惑的坚持",
    "time": 1583159448,
    "chapterName": null,
    "star": null,
    "abstract": "做生意要成功的基本原理都是相似的，困难的是真正理解其内涵并抵制诱惑的坚持。",
    "range": "689-726"
  },
  {
    "bookId": "716490",
    "content": "财报也能看k线走势",
    "time": 1583159358,
    "chapterName": null,
    "star": null,
    "abstract": "优秀者连上几个台阶，知识素养的k线走势完全呈现大牛股特征。而大多数人的能力却始终处于st的边缘。",
    "range": "262-310"
  },
  {
    "bookId": "716490",
    "content": "这就是为什么财报看五年以上",
    "time": 1583159293,
    "chapterName": null,
    "star": null,
    "abstract": "以5年的时间看企业，原本差不多的格局中优秀者脱颖而出一骑绝尘。",
    "range": "213-244"
  },
  {
    "bookId": "788330",
    "content": "",
    "time": 1567727545,
    "chapterName": null,
    "star": 100,
    "abstract": "",
    "range": ""
  },
  {
    "bookId": "813244",
    "content": "这是什么玩意儿啊",
    "time": 1573975571,
    "chapterName": null,
    "star": null,
    "abstract": "有一天，在祭神之余，公主躺在河边睡着了。恰逢此时，战神马尔斯经过她的身边，对她一见钟情。据说从天而降的马尔斯在公主熟睡之际占有了她的身体，而公主始终未醒。",
    "range": "2058-2135"
  },
  {
    "bookId": "840673",
    "content": "",
    "time": 1574403979,
    "chapterName": null,
    "star": 100,
    "abstract": "",
    "range": ""
  },
  {
    "bookId": "848184",
    "content": "",
    "time": 1576185980,
    "chapterName": null,
    "star": 100,
    "abstract": "",
    "range": ""
  },
  {
    "bookId": "856517",
    "content": "",
    "time": 1585381289,
    "chapterName": null,
    "star": 100,
    "abstract": "",
    "range": ""
  },
  {
    "bookId": "858433",
    "content": "作者最新动态是特朗普的副总统",
    "time": 1721085583,
    "chapterName": null,
    "star": 100,
    "abstract": "",
    "range": ""
  },
  {
    "bookId": "860956",
    "content": "挺好看的",
    "time": 1717249652,
    "chapterName": null,
    "star": 100,
    "abstract": "",
    "range": ""
  },
  {
    "bookId": "920788",
    "content": "",
    "time": 1566277746,
    "chapterName": null,
    "star": 100,
    "abstract": "",
    "range": ""
  },
  {
    "bookId": "927587",
    "content": "集中度提高，行业格局",
    "time": 1589616412,
    "chapterName": null,
    "star": null,
    "abstract": "投资中选择行业时，任何时候我都更喜欢低迷行业而不是热门行业。低迷行业成长缓慢，经营不善的弱者一个接一个被淘汰出局，幸存者的市场份额就会随之逐步扩大。一个公司能够在一个陷入停滞的市场上不断争取到更大的市场份额，远远胜过另一个公司在一个增长迅速的市场中费尽气力才能保住日渐萎缩的市场份额。",
    "range": "862-1004"
  },
  {
    "bookId": "928569",
    "content": "因为通胀，所以需要投资，因为投资，所以新产品新技术新科技，因为效率高，所以通胀。",
    "time": 1584233768,
    "chapterName": null,
    "star": null,
    "abstract": "假设1978年前一个家族通过勤奋努力或者各种方式积累了大量的财富，但接下来的40年里，后代如果没有能力完成这个财富传承的游戏，家道中落似乎是一种必然，所以财富管理不仅仅是一代人的事，它需要几代人持续的努力。这也许就是我们投资的根本原因。",
    "range": "2069-2187"
  },
  {
    "bookId": "928569",
    "content": "倒过来看，商品也呈现极大丰富的局面。",
    "time": 1584233561,
    "chapterName": null,
    "star": null,
    "abstract": "1930年的1美元，70年后只有0.07美元的购买力。这意味着如果我们不善待财富，“长脚的钱”会随着时间悄然流逝。",
    "range": "792-849"
  },
  {
    "bookId": "928569",
    "content": "先看历史发展，理解怎么来的",
    "time": 1584233308,
    "chapterName": null,
    "star": null,
    "abstract": "我们研究了A股15年股市历史，以及港股、美股几十年甚至上百年的股票历史，之后对股市的运行逻辑和股票的涨跌逻辑进行了深刻的剖析。",
    "range": "1846-1909"
  },
  {
    "bookId": "928569",
    "content": "道术法？\n市场表现和经营成绩不分彼此。\n商业洞察，市场理解。",
    "time": 1584233264,
    "chapterName": null,
    "star": null,
    "abstract": "有了“道”之后，要想持续成功还需要“术”。投资是困难的，不是你懂了价值投资或“买股票就是买企业的股权”这句话就可以赚钱，你还需要具备把事情做对的能力：找到优秀的企业并看准它未来的发展蓝图。对商业规律的把握，对企业估值的判断，对市场规律的认知，都需要不断地学习和积累。其实这个过程就是你学习如何“把事情做正确”，唯有这样，坚持在自己的能力圈范围之内，犯错的概率才会下降很多！",
    "range": "1616-1802"
  },
  {
    "bookId": "928569",
    "content": "商业洞察",
    "time": 1584231600,
    "chapterName": null,
    "star": null,
    "abstract": "2001年我在北京新东方参加雅思培训，感受到了新东方强大的市场影响力，很多班级都是几百人上千人的课堂，非常火爆。当时我想自己能不能搞一个这样的培训班。我首先考虑的是能不能干过新东方，调研发现在北京干不过，那么就换个地方，去西安。西安当时没有新东方分校，只有一些私人的小作坊级别的辅导班，我经过两三个月的观察认为自己干，完全能干赢他们。为什么这么说？你去看小作坊的运作思路、市场营销，就会有这个自信。当时我们并没有做教育培训的经验，但也没觉得这事做不了，好像不是很复杂，没有经验就去复制模仿，你只需要比当地市场第一名做得更好就行。这些小作坊后来一打就垮，这也印证了我对教育培训行业竞争方式的判断，即只要你成本更低、效果更好，就更有竞争优势。",
    "range": "1114-1433"
  },
  {
    "bookId": "MP_WXS_3013111951",
    "content": "",
    "time": 1610852985,
    "chapterName": null,
    "star": 20,
    "abstract": "",
    "range": ""
  }
]
