{"synckey":1671425978,"updated":[{"bookId":"35374453","bookmarkId":"35374453_35_9659-9694","chapterUid":33,"markText":"提升度=最坏分组的逾期用户数占总逾期用户数的比例／最坏分组用户数占比。","range":"9776-9811","createTime":1635294646,"type":1},{"bookId":"35374453","bookmarkId":"35374453_34_14839-14912","chapterUid":32,"markText":"业务上比较关注的长期指标一般是Mob4vintage30+，是指某一月内贷款合同签署4个月后，当前逾期30天及以上合同的未还金额／总放款合同金额。","range":"15033-15106","createTime":1635294326,"type":1},{"bookId":"35374453","bookmarkId":"35374453_34_10985-11020","chapterUid":32,"markText":"反欺诈是指识别交易诈骗、盗卡盗号等恶意欺诈行为，最大化降低公司的损失。","range":"11132-11167","createTime":1635294130,"type":1},{"bookId":"35374453","bookmarkId":"35374453_34_9966-10044","chapterUid":32,"markText":"网贷的业务逻辑最后可以用一句话来总结：依靠风控技术准确地找到目标用户，将风险控制在低水平，在合规的利率下实现盈利。由此可以看出，风控是网贷业务最核心的环节。","range":"10094-10172","createTime":1635294076,"type":1},{"bookId":"35374453","bookmarkId":"35374453_34_8786-8829","chapterUid":32,"markText":"网贷平台赚钱的业务逻辑可以概括为如下3点：靠优质客源赚钱、靠风控技术赚钱、靠引流赚钱。","range":"8886-8929","createTime":1635294020,"type":1},{"bookId":"35374453","bookmarkId":"35374453_13_3515-3548","chapterUid":12,"markText":"我们经常会说到领导力，就是把目标拆解成员工可以执行的小任务的能力。","range":"3578-3611","createTime":1615905485,"type":1},{"bookId":"35374453","bookmarkId":"35374453_8_5988-6069","chapterUid":7,"markText":"Facebook有一个著名的40-20-10法则，也就是新用户次日留存率为40%，第7日留存率为20%，第30日留存率为10%，有这个表现的产品属于数据比较好的。","range":"6126-6207","createTime":1612657193,"type":1},{"bookId":"35374453","bookmarkId":"35374453_7_844-876","chapterUid":6,"markText":"用户数据（我是谁）、行为数据（我做了什么）、产品数据（卖什么）。","range":"841-873","createTime":1612656944,"type":1}],"removed":[],"chapters":[{"title":"第6章 金融信贷行业","chapterUid":32,"chapterIdx":32},{"title":"6.2 案例分析","chapterUid":33,"chapterIdx":33},{"title":"2.2 逻辑树分析方法","chapterUid":12,"chapterIdx":12},{"title":"1.2 常用的指标有哪些？","chapterUid":7,"chapterIdx":7},{"title":"1.1 如何理解数据？","chapterUid":6,"chapterIdx":6}],"book":{"bookId":"35374453","version":1532435152,"format":"epub","soldout":0,"bookStatus":1,"cover":"https://cdn.weread.qq.com/weread/cover/68/YueWen_35374453/s_YueWen_35374453.jpg","title":"数据分析思维：分析方法和业务知识","author":"猴子·数据分析学院","coverBoxInfo":{"blurhash":"KpRf8%RkxZyGoLRk%2t6WB","colors":[{"key":"1/4","hex":"#2d1800"},{"key":"1/6","hex":"#331600"},{"key":"1/8","hex":"#391300"},{"key":"2/4","hex":"#402e07"},{"key":"2/6","hex":"#462c00"},{"key":"2/8","hex":"#4a2b00"},{"key":"3/4","hex":"#58451f"},{"key":"3/6","hex":"#5e4300"},{"key":"3/8","hex":"#614200"},{"key":"3/12","hex":"#694000"},{"key":"4/6","hex":"#795c1a"},{"key":"4/10","hex":"#805a00"},{"key":"4/4","hex":"#735d32"},{"key":"5/10","hex":"#9d7300"},{"key":"5/4","hex":"#8d774b"},{"key":"5/8","hex":"#99740e"},{"key":"6/4","hex":"#a79163"},{"key":"6/6","hex":"#af8f49"},{"key":"6/8","hex":"#b58e2c"},{"key":"6/12","hex":"#bd8c00"},{"key":"7/8","hex":"#d1a848"},{"key":"7/10","hex":"#d6a724"},{"key":"7/12","hex":"#daa600"},{"key":"8/4","hex":"#dcc694"},{"key":"8/6","hex":"#e5c57a"},{"key":"8/12","hex":"#f7c10e"},{"key":"9/2","hex":"#efe2c5"},{"key":"9/12","hex":"#ffdc34"},{"key":"1/100","hex":"#b58e2c"},{"key":"2/100","hex":"#d1a848"},{"key":"3/100","hex":"#ffffff"},{"key":"4/100","hex":"#F3F1E5"},{"key":"5/100","hex":"#F3F1E5"},{"key":"6/100","hex":"#271E00"}],"dominate_color":{"hex":"#fcc620","hsv":[45.140331945948009,87.30377938914525,98.83741406912138]},"custom_cover":"https://weread-1258476243.file.myqcloud.com/bookalphacover/453/35374453/s_35374453.jpg","custom_rec_cover":"https://weread-1258476243.file.myqcloud.com/bookreccover/453/35374453/s_35374453.jpg","colorsPure":["#bd8c00","#daa600"]}}}