{"synckey":1654350512,"updated":[{"bookId":"35459982","bookmarkId":"35459982_6_3286-3359","chapterUid":6,"markText":"“不管怎么样，人的知性还是要配合一定的肌肉才能达到平衡。可以把知性当作精神，精神和肉体也要像男人和女人一样，美好的相融合才是正道。”（三岛由纪夫）","range":"3286-3359","createTime":1654350512,"type":1},{"bookId":"35459982","bookmarkId":"35459982_3_455-503","chapterUid":3,"markText":"恶意无法像善意那样走远路。","range":"455-503","createTime":1654350414,"type":1}],"removed":[],"chapters":[{"title":"插图","chapterUid":6,"chapterIdx":6},{"title":"推荐语","chapterUid":3,"chapterIdx":3}],"book":{"bookId":"35459982","version":923568882,"format":"epub","soldout":0,"bookStatus":1,"cover":"https://cdn.weread.qq.com/weread/cover/65/YueWen_35459982/s_YueWen_35459982.jpg","title":"紫图经典文库：三岛由纪夫·潮骚","author":"三岛由纪夫","coverBoxInfo":{"blurhash":"KORMC|t6Q-?^i{kW?wX8V@","colors":[{"key":"1/4","hex":"#370e17"},{"key":"1/6","hex":"#400115"},{"key":"1/8","hex":"#480015"},{"key":"2/4","hex":"#4d2526"},{"key":"2/6","hex":"#571d21"},{"key":"2/8","hex":"#61101c"},{"key":"3/4","hex":"#693b37"},{"key":"3/6","hex":"#74342f"},{"key":"3/8","hex":"#7f2a27"},{"key":"3/12","hex":"#940016"},{"key":"4/6","hex":"#8f4d46"},{"key":"4/10","hex":"#a63d34"},{"key":"4/4","hex":"#82544f"},{"key":"5/10","hex":"#c4584a"},{"key":"5/4","hex":"#9b6e68"},{"key":"5/8","hex":"#b76154"},{"key":"6/4","hex":"#b58981"},{"key":"6/6","hex":"#c48377"},{"key":"6/8","hex":"#d27c6d"},{"key":"6/12","hex":"#ec6c58"},{"key":"7/8","hex":"#f09685"},{"key":"7/10","hex":"#fd8f7b"},{"key":"7/12","hex":"#ff866f"},{"key":"8/4","hex":"#ecbdb4"},{"key":"8/6","hex":"#fdb7a9"},{"key":"8/12","hex":"#ff9e83"},{"key":"9/2","hex":"#f2dfdb"},{"key":"9/12","hex":"#ffb79f"},{"key":"1/100","hex":"#d27c6d"},{"key":"2/100","hex":"#f09685"},{"key":"3/100","hex":"#ffffff"},{"key":"4/100","hex":"#F3E8E5"},{"key":"5/100","hex":"#F3E8E5"},{"key":"6/100","hex":"#270500"}],"dominate_color":{"hex":"#fbd6ce","hsv":[10.59493308233575,17.99965713502023,98.61725982308168]},"custom_cover":"https://weread-1258476243.file.myqcloud.com/bookalphacover/982/35459982/s_35459982.jpg","custom_rec_cover":"https://weread-1258476243.file.myqcloud.com/bookreccover/982/35459982/s_35459982.jpg","colorsPure":["#ec6c58","#ff866f"]}}}